pyramid_assetmutator/__init__.py
pyramid_assetmutator/compat.py
pyramid_assetmutator/mutator.py
pyramid_assetmutator/utils.py
pyramid_assetmutator/tests/__init__.py
pyramid_assetmutator-0.4.dist-info/DESCRIPTION.rst
pyramid_assetmutator-0.4.dist-info/METADATA
pyramid_assetmutator-0.4.dist-info/RECORD
pyramid_assetmutator-0.4.dist-info/WHEEL
pyramid_assetmutator-0.4.dist-info/metadata.json
pyramid_assetmutator-0.4.dist-info/top_level.txt
