Metadata-Version: 2.0
Name: pyramid-assetmutator
Version: 0.4
Summary: Dynamic asset mutation for Pyramid. Easily adds support for popular asset metalanguages such as CoffeeScript, SASS, SCSS, LESS, Dart, TypeScript, etc.
Home-page: http://github.com/seedifferently/pyramid_assetmutator
Author: Seth Davis
Author-email: seth@curiasolutions.com
License: MIT
Keywords: pyramid assets coffeescript sass scss less dart typescript css3
Platform: Posix; MacOS X; Windows
Classifier: Development Status :: 2 - Pre-Alpha
Classifier: Intended Audience :: Developers
Classifier: License :: OSI Approved :: MIT License
Classifier: Programming Language :: Python
Classifier: Programming Language :: Python :: 2.6
Classifier: Programming Language :: Python :: 2.7
Classifier: Programming Language :: Python :: 3
Classifier: Programming Language :: Python :: 3.2
Classifier: Programming Language :: Python :: 3.3
Classifier: Programming Language :: Python :: 3.4
Classifier: Programming Language :: Python :: Implementation :: CPython
Classifier: Programming Language :: Python :: Implementation :: PyPy
Classifier: Framework :: Pyramid
Classifier: Topic :: Internet :: WWW/HTTP
Classifier: Topic :: Internet :: WWW/HTTP :: WSGI
Classifier: Topic :: Internet :: WWW/HTTP :: Dynamic Content
Requires-Dist: pyramid (>=1.3)
